django_namespaces/__init__.py
django_namespaces/admin.py
django_namespaces/apps.py
django_namespaces/blocked.py
django_namespaces/checks.py
django_namespaces/conf.py
django_namespaces/context_processors.py
django_namespaces/decorators.py
django_namespaces/forms.py
django_namespaces/import_utils.py
django_namespaces/middleware.py
django_namespaces/mixins.py
django_namespaces/models.py
django_namespaces/namespaces.py
django_namespaces/resolvers.py
django_namespaces/services.py
django_namespaces/urls.py
django_namespaces/validators.py
django_namespaces/views.py
django_namespaces/migrations/0001_default.py
django_namespaces/migrations/__init__.py
django_namespaces/templates/base.html
django_namespaces/templates/django_namespaces/namespace_create.html
django_namespaces/templates/django_namespaces/namespace_delete.html
django_namespaces/templates/django_namespaces/namespace_list.html
django_namespaces/templates/django_namespaces/namespace_needs_activation.html
django_namespaces/templates/django_namespaces/namespace_update.html
django_namespaces/templates/django_namespaces/snippets/namespace_create.html
django_namespaces/templates/django_namespaces/snippets/namespace_list.html
django_namespaces/templates/django_namespaces/snippets/namespace_update.html
django_namespaces-0.0.27.dist-info/METADATA
django_namespaces-0.0.27.dist-info/WHEEL
django_namespaces-0.0.27.dist-info/RECORD
