Metadata-Version: 2.4
Name: django-namespaces
Version: 0.0.27
Summary: Add namespaces to your Django requests. Helps with project isolation.
Project-URL: Changelog, https://github.com/jmitchel3/django-namespaces
Project-URL: Documentation, https://github.com/jmitchel3/django-namespaces
Project-URL: Funding, https://github.com/jmitchel3/django-namespaces
Project-URL: Repository, https://github.com/jmitchel3/django-namespaces
Project-URL: Twitter, https://twitter.com/justinmitchel
Project-URL: X, https://x.com/justinmitchel
Author-email: Justin Mitchel <justin@codingforentrepreneurs.com>
License: MIT
Keywords: Django
Classifier: Development Status :: 4 - Beta
Classifier: Framework :: Django :: 4.2
Classifier: Framework :: Django :: 5.0
Classifier: Framework :: Django :: 5.1
Classifier: Intended Audience :: Developers
Classifier: License :: OSI Approved :: MIT License
Classifier: Natural Language :: English
Classifier: Operating System :: OS Independent
Classifier: Programming Language :: Python :: 3 :: Only
Classifier: Programming Language :: Python :: 3.10
Classifier: Programming Language :: Python :: 3.11
Classifier: Programming Language :: Python :: 3.12
Classifier: Programming Language :: Python :: 3.13
Classifier: Programming Language :: Python :: Implementation :: CPython
Requires-Python: >=3.10
Requires-Dist: django>=4.2
Requires-Dist: requests>=2.30
Requires-Dist: swapper>=1.4.0
